README.md
setup.cfg
setup.py
src/deab/__init__.py
src/deab/dataset.py
src/deab.egg-info/PKG-INFO
src/deab.egg-info/SOURCES.txt
src/deab.egg-info/dependency_links.txt
src/deab.egg-info/not-zip-safe
src/deab.egg-info/requires.txt
src/deab.egg-info/top_level.txt